{
  "bg": 111, 
  "temp": "absolute", 
  "snoozeBG": 158, 
  "recieved": true, 
  "predBGs": {
    "IOB": [
      111, 
      113, 
      115, 
      117, 
      120, 
      122, 
      125, 
      128, 
      131, 
      134, 
      137, 
      140, 
      143, 
      146, 
      149, 
      152, 
      155, 
      158, 
      161, 
      163, 
      166, 
      169, 
      171, 
      173, 
      176, 
      178, 
      180, 
      182, 
      184, 
      185, 
      187, 
      189, 
      190, 
      192, 
      193, 
      194, 
      195, 
      196, 
      197, 
      197, 
      198, 
      198, 
      199, 
      199, 
      199, 
      199, 
      200
    ]
  }, 
  "rate": 1.05, 
  "reason": "COB: 0, Dev: -5, BGI: 2.7, ISF: 100, Target: 135; Eventual BG 158 >= 135, temp 0.575<1.05U/hr", 
  "COB": 0, 
  "eventualBG": 158, 
  "timestamp": "2016-09-06T12:56:20.147528", 
  "duration": 30, 
  "tick": "+5", 
  "IOB": -0.645
}