[{"iob":0.122,"activity":0.0032,"bolussnooze":0.585,"basaliob":-0.663,"netbasalinsulin":-1,"hightempinsulin":0.2,"time":"2016-09-06T23:34:43.000Z"},{"iob":0.12,"activity":0.0032,"bolussnooze":0.536,"basaliob":-0.634,"netbasalinsulin":-0.95,"hightempinsulin":0.2,"time":"2016-09-06T23:39:43.000Z"},{"iob":0.12,"activity":0.0031,"bolussnooze":0.481,"basaliob":-0.605,"netbasalinsulin":-0.95,"hightempinsulin":0.2,"time":"2016-09-06T23:44:43.000Z"},{"iob":0.171,"activity":0.003,"bolussnooze":0.42,"basaliob":-0.526,"netbasalinsulin":-0.9,"hightempinsulin":0.25,"time":"2016-09-06T23:49:43.000Z"},{"iob":0.172,"activity":0.0029,"bolussnooze":0.361,"basaliob":-0.496,"netbasalinsulin":-0.9,"hightempinsulin":0.25,"time":"2016-09-06T23:54:43.000Z"},{"iob":0.174,"activity":0.0029,"bolussnooze":0.306,"basaliob":-0.466,"netbasalinsulin":-0.9,"hightempinsulin":0.25,"time":"2016-09-06T23:59:43.000Z"},{"iob":0.177,"activity":0.0029,"bolussnooze":0.256,"basaliob":-0.436,"netbasalinsulin":-0.9,"hightempinsulin":0.25,"time":"2016-09-07T00:04:43.000Z"},{"iob":0.18,"activity":0.0027,"bolussnooze":0.211,"basaliob":-0.406,"netbasalinsulin":-0.95,"hightempinsulin":0.2,"time":"2016-09-07T00:09:43.000Z"},{"iob":0.184,"activity":0.0026,"bolussnooze":0.169,"basaliob":-0.376,"netbasalinsulin":-1,"hightempinsulin":0.15,"time":"2016-09-07T00:14:43.000Z"},{"iob":0.187,"activity":0.0027,"bolussnooze":0.133,"basaliob":-0.347,"netbasalinsulin":-1,"hightempinsulin":0.15,"time":"2016-09-07T00:19:43.000Z"},{"iob":0.189,"activity":-0.0015,"bolussnooze":0.1,"basaliob":-0.319,"netbasalinsulin":-1.05,"hightempinsulin":0.1,"time":"2016-09-07T00:24:43.000Z"},{"iob":0.188,"activity":-0.0009,"bolussnooze":0.073,"basaliob":-0.292,"netbasalinsulin":-1,"hightempinsulin":0.1,"time":"2016-09-07T00:29:43.000Z"},{"iob":0.185,"activity":-0.0006,"bolussnooze":0.049,"basaliob":-0.265,"netbasalinsulin":-1,"hightempinsulin":0.1,"time":"2016-09-07T00:34:43.000Z"},{"iob":0.179,"activity":0,"bolussnooze":0.031,"basaliob":-0.239,"netbasalinsulin":-0.95,"hightempinsulin":0.1,"time":"2016-09-07T00:39:43.000Z"},{"iob":0.174,"activity":0,"bolussnooze":0.016,"basaliob":-0.214,"netbasalinsulin":-0.95,"hightempinsulin":0.1,"time":"2016-09-07T00:44:43.000Z"},{"iob":0.169,"activity":0,"bolussnooze":0.006,"basaliob":-0.191,"netbasalinsulin":-0.95,"hightempinsulin":0.1,"time":"2016-09-07T00:49:43.000Z"},{"iob":0.163,"activity":0,"bolussnooze":0.001,"basaliob":-0.169,"netbasalinsulin":-0.95,"hightempinsulin":0.1,"time":"2016-09-07T00:54:43.000Z"},{"iob":0.157,"activity":0.0001,"bolussnooze":0,"basaliob":-0.148,"netbasalinsulin":-0.95,"hightempinsulin":0.1,"time":"2016-09-07T00:59:43.000Z"},{"iob":0.15,"activity":0.0004,"bolussnooze":0,"basaliob":-0.13,"netbasalinsulin":-0.9,"hightempinsulin":0.1,"time":"2016-09-07T01:04:43.000Z"},{"iob":0.142,"activity":0.0005,"bolussnooze":0,"basaliob":-0.113,"netbasalinsulin":-0.9,"hightempinsulin":0.1,"time":"2016-09-07T01:09:43.000Z"},{"iob":0.134,"activity":0.0005,"bolussnooze":0,"basaliob":-0.098,"netbasalinsulin":-0.9,"hightempinsulin":0.1,"time":"2016-09-07T01:14:43.000Z"},{"iob":0.126,"activity":0.0006,"bolussnooze":0,"basaliob":-0.084,"netbasalinsulin":-0.9,"hightempinsulin":0.1,"time":"2016-09-07T01:19:43.000Z"},{"iob":0.117,"activity":0.0009,"bolussnooze":0,"basaliob":-0.071,"netbasalinsulin":-0.8,"hightempinsulin":0.1,"time":"2016-09-07T01:24:43.000Z"},{"iob":0.108,"activity":0.001,"bolussnooze":0,"basaliob":-0.06,"netbasalinsulin":-0.8,"hightempinsulin":0.1,"time":"2016-09-07T01:29:43.000Z"},{"iob":0.099,"activity":0.0011,"bolussnooze":0,"basaliob":-0.051,"netbasalinsulin":-0.75,"hightempinsulin":0.1,"time":"2016-09-07T01:34:43.000Z"},{"iob":0.09,"activity":0.0014,"bolussnooze":0,"basaliob":-0.042,"netbasalinsulin":-0.65,"hightempinsulin":0.1,"time":"2016-09-07T01:39:43.000Z"},{"iob":0.081,"activity":0.0014,"bolussnooze":0,"basaliob":-0.034,"netbasalinsulin":-0.65,"hightempinsulin":0.1,"time":"2016-09-07T01:44:43.000Z"},{"iob":0.073,"activity":0.0015,"bolussnooze":0,"basaliob":-0.027,"netbasalinsulin":-0.6,"hightempinsulin":0.1,"time":"2016-09-07T01:49:43.000Z"},{"iob":0.065,"activity":0.0016,"bolussnooze":0,"basaliob":-0.02,"netbasalinsulin":-0.55,"hightempinsulin":0.1,"time":"2016-09-07T01:54:43.000Z"},{"iob":0.057,"activity":0.0016,"bolussnooze":0,"basaliob":-0.015,"netbasalinsulin":-0.55,"hightempinsulin":0.1,"time":"2016-09-07T01:59:43.000Z"},{"iob":0.05,"activity":0.0016,"bolussnooze":0,"basaliob":-0.01,"netbasalinsulin":-0.55,"hightempinsulin":0.1,"time":"2016-09-07T02:04:43.000Z"},{"iob":0.042,"activity":0.0018,"bolussnooze":0,"basaliob":-0.006,"netbasalinsulin":-0.45,"hightempinsulin":0.1,"time":"2016-09-07T02:09:43.000Z"},{"iob":0.036,"activity":0.0018,"bolussnooze":0,"basaliob":-0.003,"netbasalinsulin":-0.45,"hightempinsulin":0.1,"time":"2016-09-07T02:14:43.000Z"},{"iob":0.03,"activity":0.0019,"bolussnooze":0,"basaliob":-0.001,"netbasalinsulin":-0.4,"hightempinsulin":0.1,"time":"2016-09-07T02:19:43.000Z"},{"iob":0.024,"activity":0.0018,"bolussnooze":0,"basaliob":0.002,"netbasalinsulin":-0.4,"hightempinsulin":0.1,"time":"2016-09-07T02:24:43.000Z"},{"iob":0.019,"activity":0.0019,"bolussnooze":0,"basaliob":0.003,"netbasalinsulin":-0.35,"hightempinsulin":0.1,"time":"2016-09-07T02:29:43.000Z"},{"iob":0.015,"activity":0.0019,"bolussnooze":0,"basaliob":0.004,"netbasalinsulin":-0.3,"hightempinsulin":0.1,"time":"2016-09-07T02:34:43.000Z"},{"iob":0.011,"activity":0.002,"bolussnooze":0,"basaliob":0.005,"netbasalinsulin":-0.25,"hightempinsulin":0.1,"time":"2016-09-07T02:39:43.000Z"},{"iob":0.008,"activity":0.0019,"bolussnooze":0,"basaliob":0.005,"netbasalinsulin":-0.25,"hightempinsulin":0.1,"time":"2016-09-07T02:44:43.000Z"},{"iob":0.006,"activity":0.002,"bolussnooze":0,"basaliob":0.005,"netbasalinsulin":-0.2,"hightempinsulin":0.1,"time":"2016-09-07T02:49:43.000Z"},{"iob":0.004,"activity":0.0019,"bolussnooze":0,"basaliob":0.005,"netbasalinsulin":-0.2,"hightempinsulin":0.1,"time":"2016-09-07T02:54:43.000Z"},{"iob":0.004,"activity":0.0019,"bolussnooze":0,"basaliob":0.004,"netbasalinsulin":-0.15,"hightempinsulin":0.1,"time":"2016-09-07T02:59:43.000Z"},{"iob":0.003,"activity":-0.0001,"bolussnooze":0,"basaliob":0.003,"netbasalinsulin":-0.05,"hightempinsulin":0.1,"time":"2016-09-07T03:04:43.000Z"},{"iob":0.002,"activity":0.0001,"bolussnooze":0,"basaliob":0.002,"netbasalinsulin":0,"hightempinsulin":0.1,"time":"2016-09-07T03:09:43.000Z"},{"iob":0.002,"activity":0.0001,"bolussnooze":0,"basaliob":0.002,"netbasalinsulin":0,"hightempinsulin":0.1,"time":"2016-09-07T03:14:43.000Z"},{"iob":0.001,"activity":0.0004,"bolussnooze":0,"basaliob":0.001,"netbasalinsulin":0.1,"hightempinsulin":0.1,"time":"2016-09-07T03:19:43.000Z"},{"iob":0.001,"activity":0.0004,"bolussnooze":0,"basaliob":0.001,"netbasalinsulin":0.1,"hightempinsulin":0.1,"time":"2016-09-07T03:24:43.000Z"},{"iob":0,"activity":0.0003,"bolussnooze":0,"basaliob":0,"netbasalinsulin":0.1,"hightempinsulin":0.1,"time":"2016-09-07T03:29:43.000Z"},{"iob":0,"activity":0.0002,"bolussnooze":0,"basaliob":0,"netbasalinsulin":0.05,"hightempinsulin":0.05,"time":"2016-09-07T03:34:43.000Z"},{"iob":0,"activity":0.0002,"bolussnooze":0,"basaliob":0,"netbasalinsulin":0.05,"hightempinsulin":0.05,"time":"2016-09-07T03:39:43.000Z"},{"iob":0,"activity":0.0002,"bolussnooze":0,"basaliob":0,"netbasalinsulin":0.05,"hightempinsulin":0.05,"time":"2016-09-07T03:44:43.000Z"},{"iob":0,"activity":0,"bolussnooze":0,"basaliob":0,"netbasalinsulin":0,"hightempinsulin":0,"time":"2016-09-07T03:49:43.000Z"},{"iob":0,"activity":0,"bolussnooze":0,"basaliob":0,"netbasalinsulin":0,"hightempinsulin":0,"time":"2016-09-07T03:54:43.000Z"},{"iob":0,"activity":0,"bolussnooze":0,"basaliob":0,"netbasalinsulin":0,"hightempinsulin":0,"time":"2016-09-07T03:59:43.000Z"}]
