[{"iob":2.17,"activity":0.0189,"bolussnooze":1.483,"basaliob":-0.264,"netbasalinsulin":-0.45,"hightempinsulin":0.15,"time":"2016-08-31T00:27:26.000Z"},{"iob":2.083,"activity":0.0191,"bolussnooze":1.455,"basaliob":-0.258,"netbasalinsulin":-0.4,"hightempinsulin":0.15,"time":"2016-08-31T00:32:26.000Z"},{"iob":1.997,"activity":0.0192,"bolussnooze":1.415,"basaliob":-0.252,"netbasalinsulin":-0.4,"hightempinsulin":0.15,"time":"2016-08-31T00:37:26.000Z"},{"iob":1.912,"activity":0.0192,"bolussnooze":1.363,"basaliob":-0.246,"netbasalinsulin":-0.4,"hightempinsulin":0.15,"time":"2016-08-31T00:42:26.000Z"},{"iob":1.829,"activity":0.0194,"bolussnooze":1.298,"basaliob":-0.239,"netbasalinsulin":-0.35,"hightempinsulin":0.15,"time":"2016-08-31T00:47:26.000Z"},{"iob":1.746,"activity":0.0195,"bolussnooze":1.22,"basaliob":-0.232,"netbasalinsulin":-0.35,"hightempinsulin":0.15,"time":"2016-08-31T00:52:26.000Z"},{"iob":1.665,"activity":0.0195,"bolussnooze":1.13,"basaliob":-0.225,"netbasalinsulin":-0.35,"hightempinsulin":0.15,"time":"2016-08-31T00:57:26.000Z"},{"iob":1.585,"activity":0.0196,"bolussnooze":1.028,"basaliob":-0.218,"netbasalinsulin":-0.35,"hightempinsulin":0.15,"time":"2016-08-31T01:02:26.000Z"},{"iob":1.506,"activity":0.0198,"bolussnooze":0.913,"basaliob":-0.21,"netbasalinsulin":-0.3,"hightempinsulin":0.15,"time":"2016-08-31T01:07:26.000Z"},{"iob":1.428,"activity":0.0198,"bolussnooze":0.79,"basaliob":-0.202,"netbasalinsulin":-0.3,"hightempinsulin":0.15,"time":"2016-08-31T01:12:26.000Z"},{"iob":1.351,"activity":0.0199,"bolussnooze":0.675,"basaliob":-0.194,"netbasalinsulin":-0.3,"hightempinsulin":0.15,"time":"2016-08-31T01:17:26.000Z"},{"iob":1.276,"activity":0.0201,"bolussnooze":0.57,"basaliob":-0.186,"netbasalinsulin":-0.25,"hightempinsulin":0.15,"time":"2016-08-31T01:22:26.000Z"},{"iob":1.202,"activity":0.0201,"bolussnooze":0.473,"basaliob":-0.177,"netbasalinsulin":-0.25,"hightempinsulin":0.15,"time":"2016-08-31T01:27:26.000Z"},{"iob":1.129,"activity":0.0202,"bolussnooze":0.386,"basaliob":-0.168,"netbasalinsulin":-0.25,"hightempinsulin":0.15,"time":"2016-08-31T01:32:26.000Z"},{"iob":1.057,"activity":0.0202,"bolussnooze":0.307,"basaliob":-0.159,"netbasalinsulin":-0.25,"hightempinsulin":0.15,"time":"2016-08-31T01:37:26.000Z"},{"iob":0.986,"activity":0.0202,"bolussnooze":0.238,"basaliob":-0.149,"netbasalinsulin":-0.25,"hightempinsulin":0.15,"time":"2016-08-31T01:42:26.000Z"},{"iob":0.917,"activity":0.0201,"bolussnooze":0.177,"basaliob":-0.139,"netbasalinsulin":-0.3,"hightempinsulin":0.1,"time":"2016-08-31T01:47:26.000Z"},{"iob":0.848,"activity":0.0201,"bolussnooze":0.125,"basaliob":-0.129,"netbasalinsulin":-0.35,"hightempinsulin":0.05,"time":"2016-08-31T01:52:26.000Z"},{"iob":0.781,"activity":0.0202,"bolussnooze":0.082,"basaliob":-0.119,"netbasalinsulin":-0.35,"hightempinsulin":0,"time":"2016-08-31T01:57:26.000Z"},{"iob":0.715,"activity":0.02,"bolussnooze":0.048,"basaliob":-0.109,"netbasalinsulin":-0.35,"hightempinsulin":0,"time":"2016-08-31T02:02:26.000Z"},{"iob":0.657,"activity":0.0192,"bolussnooze":0.023,"basaliob":-0.1,"netbasalinsulin":-0.35,"hightempinsulin":0,"time":"2016-08-31T02:07:26.000Z"},{"iob":0.604,"activity":0.0185,"bolussnooze":0.007,"basaliob":-0.092,"netbasalinsulin":-0.35,"hightempinsulin":0,"time":"2016-08-31T02:12:26.000Z"},{"iob":0.557,"activity":0.0179,"bolussnooze":0,"basaliob":-0.084,"netbasalinsulin":-0.3,"hightempinsulin":0,"time":"2016-08-31T02:17:26.000Z"},{"iob":0.512,"activity":0.0094,"bolussnooze":0,"basaliob":-0.076,"netbasalinsulin":-0.3,"hightempinsulin":0,"time":"2016-08-31T02:22:26.000Z"},{"iob":0.469,"activity":0.0091,"bolussnooze":0,"basaliob":-0.069,"netbasalinsulin":-0.3,"hightempinsulin":0,"time":"2016-08-31T02:27:26.000Z"},{"iob":0.428,"activity":0.0089,"bolussnooze":0,"basaliob":-0.062,"netbasalinsulin":-0.3,"hightempinsulin":0,"time":"2016-08-31T02:32:26.000Z"},{"iob":0.389,"activity":0.0087,"bolussnooze":0,"basaliob":-0.056,"netbasalinsulin":-0.3,"hightempinsulin":0,"time":"2016-08-31T02:37:26.000Z"},{"iob":0.351,"activity":0.0086,"bolussnooze":0,"basaliob":-0.05,"netbasalinsulin":-0.25,"hightempinsulin":0,"time":"2016-08-31T02:42:26.000Z"},{"iob":0.316,"activity":0.0084,"bolussnooze":0,"basaliob":-0.044,"netbasalinsulin":-0.25,"hightempinsulin":0,"time":"2016-08-31T02:47:26.000Z"},{"iob":0.282,"activity":0.0081,"bolussnooze":0,"basaliob":-0.039,"netbasalinsulin":-0.25,"hightempinsulin":0,"time":"2016-08-31T02:52:26.000Z"},{"iob":0.25,"activity":0.0079,"bolussnooze":0,"basaliob":-0.034,"netbasalinsulin":-0.25,"hightempinsulin":0,"time":"2016-08-31T02:57:26.000Z"},{"iob":0.22,"activity":0.0077,"bolussnooze":0,"basaliob":-0.03,"netbasalinsulin":-0.25,"hightempinsulin":0,"time":"2016-08-31T03:02:26.000Z"},{"iob":0.191,"activity":0.0076,"bolussnooze":0,"basaliob":-0.026,"netbasalinsulin":-0.2,"hightempinsulin":0,"time":"2016-08-31T03:07:26.000Z"},{"iob":0.165,"activity":0.0073,"bolussnooze":0,"basaliob":-0.022,"netbasalinsulin":-0.2,"hightempinsulin":0,"time":"2016-08-31T03:12:26.000Z"},{"iob":0.141,"activity":0.0071,"bolussnooze":0,"basaliob":-0.019,"netbasalinsulin":-0.2,"hightempinsulin":0,"time":"2016-08-31T03:17:26.000Z"},{"iob":0.118,"activity":0.0068,"bolussnooze":0,"basaliob":-0.016,"netbasalinsulin":-0.2,"hightempinsulin":0,"time":"2016-08-31T03:22:26.000Z"},{"iob":0.098,"activity":0.0066,"bolussnooze":0,"basaliob":-0.013,"netbasalinsulin":-0.2,"hightempinsulin":0,"time":"2016-08-31T03:27:26.000Z"},{"iob":0.079,"activity":0.0063,"bolussnooze":0,"basaliob":-0.01,"netbasalinsulin":-0.2,"hightempinsulin":0,"time":"2016-08-31T03:32:26.000Z"},{"iob":0.063,"activity":0.0061,"bolussnooze":0,"basaliob":-0.008,"netbasalinsulin":-0.2,"hightempinsulin":0,"time":"2016-08-31T03:37:26.000Z"},{"iob":0.048,"activity":0.0059,"bolussnooze":0,"basaliob":-0.006,"netbasalinsulin":-0.2,"hightempinsulin":0,"time":"2016-08-31T03:42:26.000Z"},{"iob":0.035,"activity":0.0056,"bolussnooze":0,"basaliob":-0.004,"netbasalinsulin":-0.2,"hightempinsulin":0,"time":"2016-08-31T03:47:26.000Z"},{"iob":0.024,"activity":0.0054,"bolussnooze":0,"basaliob":-0.003,"netbasalinsulin":-0.2,"hightempinsulin":0,"time":"2016-08-31T03:52:26.000Z"},{"iob":0.015,"activity":0.0051,"bolussnooze":0,"basaliob":-0.002,"netbasalinsulin":-0.2,"hightempinsulin":0,"time":"2016-08-31T03:57:26.000Z"},{"iob":0.009,"activity":0.0049,"bolussnooze":0,"basaliob":-0.001,"netbasalinsulin":-0.2,"hightempinsulin":0,"time":"2016-08-31T04:02:26.000Z"},{"iob":0.004,"activity":0.0048,"bolussnooze":0,"basaliob":0,"netbasalinsulin":-0.15,"hightempinsulin":0,"time":"2016-08-31T04:07:26.000Z"},{"iob":0.001,"activity":0.0045,"bolussnooze":0,"basaliob":0,"netbasalinsulin":-0.15,"hightempinsulin":0,"time":"2016-08-31T04:12:26.000Z"},{"iob":0,"activity":0.0044,"bolussnooze":0,"basaliob":0,"netbasalinsulin":-0.1,"hightempinsulin":0,"time":"2016-08-31T04:17:26.000Z"},{"iob":0,"activity":-0.0002,"bolussnooze":0,"basaliob":0,"netbasalinsulin":-0.05,"hightempinsulin":0,"time":"2016-08-31T04:22:26.000Z"},{"iob":0,"activity":0,"bolussnooze":0,"basaliob":0,"netbasalinsulin":0,"hightempinsulin":0,"time":"2016-08-31T04:27:26.000Z"},{"iob":0,"activity":0,"bolussnooze":0,"basaliob":0,"netbasalinsulin":0,"hightempinsulin":0,"time":"2016-08-31T04:32:26.000Z"},{"iob":0,"activity":0,"bolussnooze":0,"basaliob":0,"netbasalinsulin":0,"hightempinsulin":0,"time":"2016-08-31T04:37:26.000Z"},{"iob":0,"activity":0,"bolussnooze":0,"basaliob":0,"netbasalinsulin":0,"hightempinsulin":0,"time":"2016-08-31T04:42:26.000Z"},{"iob":0,"activity":0,"bolussnooze":0,"basaliob":0,"netbasalinsulin":0,"hightempinsulin":0,"time":"2016-08-31T04:47:26.000Z"},{"iob":0,"activity":0,"bolussnooze":0,"basaliob":0,"netbasalinsulin":0,"hightempinsulin":0,"time":"2016-08-31T04:52:26.000Z"}]
