[{"iob":-0.615,"activity":-0.005,"bolussnooze":0,"basaliob":-0.615,"netbasalinsulin":-1.05,"hightempinsulin":0,"time":"2016-08-31T15:23:32.000Z"},{"iob":-0.592,"activity":-0.0052,"bolussnooze":0,"basaliob":-0.592,"netbasalinsulin":-1.05,"hightempinsulin":0,"time":"2016-08-31T15:28:32.000Z"},{"iob":-0.569,"activity":-0.0053,"bolussnooze":0,"basaliob":-0.569,"netbasalinsulin":-1.05,"hightempinsulin":0,"time":"2016-08-31T15:33:32.000Z"},{"iob":-0.546,"activity":-0.0053,"bolussnooze":0,"basaliob":-0.546,"netbasalinsulin":-1,"hightempinsulin":0,"time":"2016-08-31T15:38:32.000Z"},{"iob":-0.522,"activity":-0.0054,"bolussnooze":0,"basaliob":-0.522,"netbasalinsulin":-1,"hightempinsulin":0,"time":"2016-08-31T15:43:32.000Z"},{"iob":-0.498,"activity":-0.0054,"bolussnooze":0,"basaliob":-0.498,"netbasalinsulin":-0.95,"hightempinsulin":0,"time":"2016-08-31T15:48:32.000Z"},{"iob":-0.474,"activity":-0.0052,"bolussnooze":0,"basaliob":-0.474,"netbasalinsulin":-0.85,"hightempinsulin":0,"time":"2016-08-31T15:53:32.000Z"},{"iob":-0.45,"activity":-0.0053,"bolussnooze":0,"basaliob":-0.45,"netbasalinsulin":-0.85,"hightempinsulin":0,"time":"2016-08-31T15:58:32.000Z"},{"iob":-0.425,"activity":-0.0053,"bolussnooze":0,"basaliob":-0.425,"netbasalinsulin":-0.85,"hightempinsulin":0,"time":"2016-08-31T16:03:32.000Z"},{"iob":-0.401,"activity":-0.0054,"bolussnooze":0,"basaliob":-0.401,"netbasalinsulin":-0.85,"hightempinsulin":0,"time":"2016-08-31T16:08:32.000Z"},{"iob":-0.376,"activity":-0.0055,"bolussnooze":0,"basaliob":-0.376,"netbasalinsulin":-0.85,"hightempinsulin":0,"time":"2016-08-31T16:13:32.000Z"},{"iob":-0.351,"activity":-0.0056,"bolussnooze":0,"basaliob":-0.351,"netbasalinsulin":-0.85,"hightempinsulin":0,"time":"2016-08-31T16:18:32.000Z"},{"iob":-0.326,"activity":-0.0056,"bolussnooze":0,"basaliob":-0.326,"netbasalinsulin":-0.85,"hightempinsulin":0,"time":"2016-08-31T16:23:32.000Z"},{"iob":-0.302,"activity":-0.0056,"bolussnooze":0,"basaliob":-0.302,"netbasalinsulin":-0.85,"hightempinsulin":0,"time":"2016-08-31T16:28:32.000Z"},{"iob":-0.278,"activity":-0.0056,"bolussnooze":0,"basaliob":-0.278,"netbasalinsulin":-0.85,"hightempinsulin":0,"time":"2016-08-31T16:33:32.000Z"},{"iob":-0.254,"activity":-0.0055,"bolussnooze":0,"basaliob":-0.254,"netbasalinsulin":-0.85,"hightempinsulin":0,"time":"2016-08-31T16:38:32.000Z"},{"iob":-0.232,"activity":-0.0053,"bolussnooze":0,"basaliob":-0.232,"netbasalinsulin":-0.8,"hightempinsulin":0,"time":"2016-08-31T16:43:32.000Z"},{"iob":-0.211,"activity":-0.0052,"bolussnooze":0,"basaliob":-0.211,"netbasalinsulin":-0.8,"hightempinsulin":0,"time":"2016-08-31T16:48:32.000Z"},{"iob":-0.191,"activity":-0.005,"bolussnooze":0,"basaliob":-0.191,"netbasalinsulin":-0.8,"hightempinsulin":0,"time":"2016-08-31T16:53:32.000Z"},{"iob":-0.172,"activity":-0.0048,"bolussnooze":0,"basaliob":-0.172,"netbasalinsulin":-0.8,"hightempinsulin":0,"time":"2016-08-31T16:58:32.000Z"},{"iob":-0.154,"activity":-0.0047,"bolussnooze":0,"basaliob":-0.154,"netbasalinsulin":-0.8,"hightempinsulin":0,"time":"2016-08-31T17:03:32.000Z"},{"iob":-0.138,"activity":-0.0045,"bolussnooze":0,"basaliob":-0.138,"netbasalinsulin":-0.8,"hightempinsulin":0,"time":"2016-08-31T17:08:32.000Z"},{"iob":-0.123,"activity":-0.0044,"bolussnooze":0,"basaliob":-0.123,"netbasalinsulin":-0.8,"hightempinsulin":0,"time":"2016-08-31T17:13:32.000Z"},{"iob":-0.109,"activity":-0.0042,"bolussnooze":0,"basaliob":-0.109,"netbasalinsulin":-0.8,"hightempinsulin":0,"time":"2016-08-31T17:18:32.000Z"},{"iob":-0.096,"activity":-0.0039,"bolussnooze":0,"basaliob":-0.096,"netbasalinsulin":-0.75,"hightempinsulin":0,"time":"2016-08-31T17:23:32.000Z"},{"iob":-0.084,"activity":-0.0037,"bolussnooze":0,"basaliob":-0.084,"netbasalinsulin":-0.7,"hightempinsulin":0,"time":"2016-08-31T17:28:32.000Z"},{"iob":-0.073,"activity":-0.0034,"bolussnooze":0,"basaliob":-0.073,"netbasalinsulin":-0.65,"hightempinsulin":0,"time":"2016-08-31T17:33:32.000Z"},{"iob":-0.063,"activity":-0.0031,"bolussnooze":0,"basaliob":-0.063,"netbasalinsulin":-0.6,"hightempinsulin":0,"time":"2016-08-31T17:38:32.000Z"},{"iob":-0.054,"activity":-0.003,"bolussnooze":0,"basaliob":-0.054,"netbasalinsulin":-0.6,"hightempinsulin":0,"time":"2016-08-31T17:43:32.000Z"},{"iob":-0.046,"activity":-0.0029,"bolussnooze":0,"basaliob":-0.046,"netbasalinsulin":-0.6,"hightempinsulin":0,"time":"2016-08-31T17:48:32.000Z"},{"iob":-0.038,"activity":-0.0026,"bolussnooze":0,"basaliob":-0.038,"netbasalinsulin":-0.55,"hightempinsulin":0,"time":"2016-08-31T17:53:32.000Z"},{"iob":-0.032,"activity":-0.0024,"bolussnooze":0,"basaliob":-0.032,"netbasalinsulin":-0.5,"hightempinsulin":0,"time":"2016-08-31T17:58:32.000Z"},{"iob":-0.026,"activity":-0.0021,"bolussnooze":0,"basaliob":-0.026,"netbasalinsulin":-0.45,"hightempinsulin":0,"time":"2016-08-31T18:03:32.000Z"},{"iob":-0.021,"activity":-0.002,"bolussnooze":0,"basaliob":-0.021,"netbasalinsulin":-0.45,"hightempinsulin":0,"time":"2016-08-31T18:08:32.000Z"},{"iob":-0.016,"activity":-0.002,"bolussnooze":0,"basaliob":-0.016,"netbasalinsulin":-0.45,"hightempinsulin":0,"time":"2016-08-31T18:13:32.000Z"},{"iob":-0.012,"activity":-0.0017,"bolussnooze":0,"basaliob":-0.012,"netbasalinsulin":-0.4,"hightempinsulin":0,"time":"2016-08-31T18:18:32.000Z"},{"iob":-0.009,"activity":-0.0016,"bolussnooze":0,"basaliob":-0.009,"netbasalinsulin":-0.4,"hightempinsulin":0,"time":"2016-08-31T18:23:32.000Z"},{"iob":-0.006,"activity":-0.0016,"bolussnooze":0,"basaliob":-0.006,"netbasalinsulin":-0.4,"hightempinsulin":0,"time":"2016-08-31T18:28:32.000Z"},{"iob":-0.004,"activity":-0.0015,"bolussnooze":0,"basaliob":-0.004,"netbasalinsulin":-0.4,"hightempinsulin":0,"time":"2016-08-31T18:33:32.000Z"},{"iob":-0.002,"activity":-0.0013,"bolussnooze":0,"basaliob":-0.002,"netbasalinsulin":-0.35,"hightempinsulin":0,"time":"2016-08-31T18:38:32.000Z"},{"iob":-0.001,"activity":-0.0011,"bolussnooze":0,"basaliob":-0.001,"netbasalinsulin":-0.3,"hightempinsulin":0,"time":"2016-08-31T18:43:32.000Z"},{"iob":-0.001,"activity":-0.0009,"bolussnooze":0,"basaliob":-0.001,"netbasalinsulin":-0.25,"hightempinsulin":0,"time":"2016-08-31T18:48:32.000Z"},{"iob":0,"activity":-0.0007,"bolussnooze":0,"basaliob":0,"netbasalinsulin":-0.2,"hightempinsulin":0,"time":"2016-08-31T18:53:32.000Z"},{"iob":0,"activity":-0.0005,"bolussnooze":0,"basaliob":0,"netbasalinsulin":-0.15,"hightempinsulin":0,"time":"2016-08-31T18:58:32.000Z"},{"iob":0,"activity":-0.0002,"bolussnooze":0,"basaliob":0,"netbasalinsulin":-0.05,"hightempinsulin":0,"time":"2016-08-31T19:03:32.000Z"},{"iob":0,"activity":0,"bolussnooze":0,"basaliob":0,"netbasalinsulin":0,"hightempinsulin":0,"time":"2016-08-31T19:08:32.000Z"},{"iob":0,"activity":0,"bolussnooze":0,"basaliob":0,"netbasalinsulin":0,"hightempinsulin":0,"time":"2016-08-31T19:13:32.000Z"},{"iob":0,"activity":0,"bolussnooze":0,"basaliob":0,"netbasalinsulin":0,"hightempinsulin":0,"time":"2016-08-31T19:18:32.000Z"},{"iob":0,"activity":0,"bolussnooze":0,"basaliob":0,"netbasalinsulin":0,"hightempinsulin":0,"time":"2016-08-31T19:23:32.000Z"},{"iob":0,"activity":0,"bolussnooze":0,"basaliob":0,"netbasalinsulin":0,"hightempinsulin":0,"time":"2016-08-31T19:28:32.000Z"},{"iob":0,"activity":0,"bolussnooze":0,"basaliob":0,"netbasalinsulin":0,"hightempinsulin":0,"time":"2016-08-31T19:33:32.000Z"},{"iob":0,"activity":0,"bolussnooze":0,"basaliob":0,"netbasalinsulin":0,"hightempinsulin":0,"time":"2016-08-31T19:38:32.000Z"},{"iob":0,"activity":0,"bolussnooze":0,"basaliob":0,"netbasalinsulin":0,"hightempinsulin":0,"time":"2016-08-31T19:43:32.000Z"},{"iob":0,"activity":0,"bolussnooze":0,"basaliob":0,"netbasalinsulin":0,"hightempinsulin":0,"time":"2016-08-31T19:48:32.000Z"}]
