[{"iob":0.786,"activity":0.0163,"bolussnooze":0.187,"basaliob":-0.349,"netbasalinsulin":0.25,"hightempinsulin":0.75,"time":"2016-09-03T05:23:32.000Z"},{"iob":0.662,"activity":0.0164,"bolussnooze":0.134,"basaliob":-0.404,"netbasalinsulin":0.15,"hightempinsulin":0.7,"time":"2016-09-03T05:28:32.000Z"},{"iob":0.537,"activity":0.0166,"bolussnooze":0.089,"basaliob":-0.457,"netbasalinsulin":0.1,"hightempinsulin":0.7,"time":"2016-09-03T05:33:32.000Z"},{"iob":0.412,"activity":0.0167,"bolussnooze":0.054,"basaliob":-0.508,"netbasalinsulin":0.05,"hightempinsulin":0.7,"time":"2016-09-03T05:38:32.000Z"},{"iob":0.344,"activity":0.016,"bolussnooze":0.027,"basaliob":-0.506,"netbasalinsulin":0.05,"hightempinsulin":0.7,"time":"2016-09-03T05:43:32.000Z"},{"iob":0.28,"activity":0.0152,"bolussnooze":0.009,"basaliob":-0.503,"netbasalinsulin":0.05,"hightempinsulin":0.7,"time":"2016-09-03T05:48:32.000Z"},{"iob":0.221,"activity":0.0142,"bolussnooze":0.001,"basaliob":-0.498,"netbasalinsulin":-0.05,"hightempinsulin":0.6,"time":"2016-09-03T05:53:32.000Z"},{"iob":0.166,"activity":0.0134,"bolussnooze":0,"basaliob":-0.491,"netbasalinsulin":-0.1,"hightempinsulin":0.55,"time":"2016-09-03T05:58:32.000Z"},{"iob":0.117,"activity":0.0126,"bolussnooze":0,"basaliob":-0.482,"netbasalinsulin":-0.15,"hightempinsulin":0.5,"time":"2016-09-03T06:03:32.000Z"},{"iob":0.071,"activity":0.0118,"bolussnooze":0,"basaliob":-0.471,"netbasalinsulin":-0.2,"hightempinsulin":0.45,"time":"2016-09-03T06:08:32.000Z"},{"iob":0.03,"activity":0.011,"bolussnooze":0,"basaliob":-0.459,"netbasalinsulin":-0.25,"hightempinsulin":0.4,"time":"2016-09-03T06:13:32.000Z"},{"iob":-0.006,"activity":0.0102,"bolussnooze":0,"basaliob":-0.445,"netbasalinsulin":-0.3,"hightempinsulin":0.35,"time":"2016-09-03T06:18:32.000Z"},{"iob":-0.038,"activity":0.0096,"bolussnooze":0,"basaliob":-0.43,"netbasalinsulin":-0.3,"hightempinsulin":0.35,"time":"2016-09-03T06:23:32.000Z"},{"iob":-0.066,"activity":0.0088,"bolussnooze":0,"basaliob":-0.414,"netbasalinsulin":-0.35,"hightempinsulin":0.3,"time":"2016-09-03T06:28:32.000Z"},{"iob":-0.09,"activity":0.008,"bolussnooze":0,"basaliob":-0.396,"netbasalinsulin":-0.4,"hightempinsulin":0.25,"time":"2016-09-03T06:33:32.000Z"},{"iob":-0.109,"activity":0.0073,"bolussnooze":0,"basaliob":-0.376,"netbasalinsulin":-0.45,"hightempinsulin":0.2,"time":"2016-09-03T06:38:32.000Z"},{"iob":-0.125,"activity":0.0067,"bolussnooze":0,"basaliob":-0.356,"netbasalinsulin":-0.45,"hightempinsulin":0.2,"time":"2016-09-03T06:43:32.000Z"},{"iob":-0.138,"activity":0.0059,"bolussnooze":0,"basaliob":-0.335,"netbasalinsulin":-0.55,"hightempinsulin":0.1,"time":"2016-09-03T06:48:32.000Z"},{"iob":-0.147,"activity":0.0055,"bolussnooze":0,"basaliob":-0.314,"netbasalinsulin":-0.55,"hightempinsulin":0.05,"time":"2016-09-03T06:53:32.000Z"},{"iob":-0.154,"activity":0.0049,"bolussnooze":0,"basaliob":-0.293,"netbasalinsulin":-0.6,"hightempinsulin":0,"time":"2016-09-03T06:58:32.000Z"},{"iob":-0.157,"activity":0.0045,"bolussnooze":0,"basaliob":-0.272,"netbasalinsulin":-0.6,"hightempinsulin":0,"time":"2016-09-03T07:03:32.000Z"},{"iob":-0.159,"activity":0.0042,"bolussnooze":0,"basaliob":-0.252,"netbasalinsulin":-0.6,"hightempinsulin":0,"time":"2016-09-03T07:08:32.000Z"},{"iob":-0.158,"activity":0.0027,"bolussnooze":0,"basaliob":-0.232,"netbasalinsulin":-0.6,"hightempinsulin":0,"time":"2016-09-03T07:13:32.000Z"},{"iob":-0.156,"activity":0.0027,"bolussnooze":0,"basaliob":-0.213,"netbasalinsulin":-0.55,"hightempinsulin":0,"time":"2016-09-03T07:18:32.000Z"},{"iob":-0.153,"activity":0.0025,"bolussnooze":0,"basaliob":-0.195,"netbasalinsulin":-0.55,"hightempinsulin":0,"time":"2016-09-03T07:23:32.000Z"},{"iob":-0.148,"activity":0.0023,"bolussnooze":0,"basaliob":-0.178,"netbasalinsulin":-0.55,"hightempinsulin":0,"time":"2016-09-03T07:28:32.000Z"},{"iob":-0.142,"activity":0.0021,"bolussnooze":0,"basaliob":-0.161,"netbasalinsulin":-0.55,"hightempinsulin":0,"time":"2016-09-03T07:33:32.000Z"},{"iob":-0.135,"activity":0.0019,"bolussnooze":0,"basaliob":-0.145,"netbasalinsulin":-0.55,"hightempinsulin":0,"time":"2016-09-03T07:38:32.000Z"},{"iob":-0.126,"activity":0.0018,"bolussnooze":0,"basaliob":-0.13,"netbasalinsulin":-0.55,"hightempinsulin":0,"time":"2016-09-03T07:43:32.000Z"},{"iob":-0.115,"activity":0.0016,"bolussnooze":0,"basaliob":-0.116,"netbasalinsulin":-0.55,"hightempinsulin":0,"time":"2016-09-03T07:48:32.000Z"},{"iob":-0.103,"activity":0.0014,"bolussnooze":0,"basaliob":-0.103,"netbasalinsulin":-0.55,"hightempinsulin":0,"time":"2016-09-03T07:53:32.000Z"},{"iob":-0.091,"activity":-0.0033,"bolussnooze":0,"basaliob":-0.091,"netbasalinsulin":-0.55,"hightempinsulin":0,"time":"2016-09-03T07:58:32.000Z"},{"iob":-0.079,"activity":-0.0032,"bolussnooze":0,"basaliob":-0.079,"netbasalinsulin":-0.55,"hightempinsulin":0,"time":"2016-09-03T08:03:32.000Z"},{"iob":-0.068,"activity":-0.0031,"bolussnooze":0,"basaliob":-0.068,"netbasalinsulin":-0.55,"hightempinsulin":0,"time":"2016-09-03T08:08:32.000Z"},{"iob":-0.058,"activity":-0.003,"bolussnooze":0,"basaliob":-0.058,"netbasalinsulin":-0.55,"hightempinsulin":0,"time":"2016-09-03T08:13:32.000Z"},{"iob":-0.049,"activity":-0.0028,"bolussnooze":0,"basaliob":-0.049,"netbasalinsulin":-0.55,"hightempinsulin":0,"time":"2016-09-03T08:18:32.000Z"},{"iob":-0.041,"activity":-0.0027,"bolussnooze":0,"basaliob":-0.041,"netbasalinsulin":-0.55,"hightempinsulin":0,"time":"2016-09-03T08:23:32.000Z"},{"iob":-0.033,"activity":-0.0026,"bolussnooze":0,"basaliob":-0.033,"netbasalinsulin":-0.55,"hightempinsulin":0,"time":"2016-09-03T08:28:32.000Z"},{"iob":-0.027,"activity":-0.0025,"bolussnooze":0,"basaliob":-0.027,"netbasalinsulin":-0.55,"hightempinsulin":0,"time":"2016-09-03T08:33:32.000Z"},{"iob":-0.021,"activity":-0.0024,"bolussnooze":0,"basaliob":-0.021,"netbasalinsulin":-0.55,"hightempinsulin":0,"time":"2016-09-03T08:38:32.000Z"},{"iob":-0.016,"activity":-0.0023,"bolussnooze":0,"basaliob":-0.016,"netbasalinsulin":-0.55,"hightempinsulin":0,"time":"2016-09-03T08:43:32.000Z"},{"iob":-0.011,"activity":-0.0022,"bolussnooze":0,"basaliob":-0.011,"netbasalinsulin":-0.55,"hightempinsulin":0,"time":"2016-09-03T08:48:32.000Z"},{"iob":-0.008,"activity":-0.0021,"bolussnooze":0,"basaliob":-0.008,"netbasalinsulin":-0.55,"hightempinsulin":0,"time":"2016-09-03T08:53:32.000Z"},{"iob":-0.005,"activity":-0.0019,"bolussnooze":0,"basaliob":-0.005,"netbasalinsulin":-0.5,"hightempinsulin":0,"time":"2016-09-03T08:58:32.000Z"},{"iob":-0.003,"activity":-0.0015,"bolussnooze":0,"basaliob":-0.003,"netbasalinsulin":-0.4,"hightempinsulin":0,"time":"2016-09-03T09:03:32.000Z"},{"iob":-0.002,"activity":-0.0013,"bolussnooze":0,"basaliob":-0.002,"netbasalinsulin":-0.35,"hightempinsulin":0,"time":"2016-09-03T09:08:32.000Z"},{"iob":-0.001,"activity":-0.001,"bolussnooze":0,"basaliob":-0.001,"netbasalinsulin":-0.3,"hightempinsulin":0,"time":"2016-09-03T09:13:32.000Z"},{"iob":0,"activity":-0.0008,"bolussnooze":0,"basaliob":0,"netbasalinsulin":-0.25,"hightempinsulin":0,"time":"2016-09-03T09:18:32.000Z"},{"iob":0,"activity":-0.0005,"bolussnooze":0,"basaliob":0,"netbasalinsulin":-0.15,"hightempinsulin":0,"time":"2016-09-03T09:23:32.000Z"},{"iob":0,"activity":-0.0003,"bolussnooze":0,"basaliob":0,"netbasalinsulin":-0.1,"hightempinsulin":0,"time":"2016-09-03T09:28:32.000Z"},{"iob":0,"activity":-0.0002,"bolussnooze":0,"basaliob":0,"netbasalinsulin":-0.05,"hightempinsulin":0,"time":"2016-09-03T09:33:32.000Z"},{"iob":0,"activity":0,"bolussnooze":0,"basaliob":0,"netbasalinsulin":0,"hightempinsulin":0,"time":"2016-09-03T09:38:32.000Z"},{"iob":0,"activity":0,"bolussnooze":0,"basaliob":0,"netbasalinsulin":0,"hightempinsulin":0,"time":"2016-09-03T09:43:32.000Z"},{"iob":0,"activity":0,"bolussnooze":0,"basaliob":0,"netbasalinsulin":0,"hightempinsulin":0,"time":"2016-09-03T09:48:32.000Z"}]
